setup.py
django_gunicorn/__init__.py
django_gunicorn.egg-info/PKG-INFO
django_gunicorn.egg-info/SOURCES.txt
django_gunicorn.egg-info/dependency_links.txt
django_gunicorn.egg-info/not-zip-safe
django_gunicorn.egg-info/requires.txt
django_gunicorn.egg-info/top_level.txt
django_gunicorn/management/__init__.py
django_gunicorn/management/commands/__init__.py
django_gunicorn/management/commands/runserver.py